masks_fp/__init__.py
masks_fp/library/__init__.py
masks_fp/library/merge_signatures.py
masks_fp/library/set_return_annotations.py
masks_fp/masks.py
masks_fp/type/__init__.py
masks_fp/type/types.py
masks_fp-1.0.0.dist-info/LICENSE
masks_fp-1.0.0.dist-info/METADATA
masks_fp-1.0.0.dist-info/WHEEL
masks_fp-1.0.0.dist-info/RECORD
