Metadata-Version: 2.3
Name: masks-fp
Version: 1.0.0
Summary: Masks fp is a powerful wrapping tool that preserves meta and anatomical information. 🎭
License: MIT
Keywords: python,wrapper,functional-programming,tool,fp
Author: A-4S
Author-email: dev.forsythe@gmail.com
Requires-Python: >=3.10
Classifier: License :: OSI Approved :: MIT License
Classifier: Programming Language :: Python :: 3
Classifier: Programming Language :: Python :: 3.10
Classifier: Programming Language :: Python :: 3.11
Classifier: Programming Language :: Python :: 3.12
Classifier: Programming Language :: Python :: 3.13
Requires-Dist: pipe-fp (>=2.0.0,<3.0.0)
